metlib/__init__.py
metlib/functions.py
metlib-0.0.1.3.dist-info/LICENSE
metlib-0.0.1.3.dist-info/METADATA
metlib-0.0.1.3.dist-info/WHEEL
metlib-0.0.1.3.dist-info/top_level.txt
metlib-0.0.1.3.dist-info/RECORD
