Metadata-Version: 2.1
Name: metlib
Version: 0.0.1.3
Summary: Python package to performs meteorological calculations
Home-page: https://github.com/joaohenry23/metlib
Author: Joao Henry Huamán Chinchay
Author-email: joaohenry23@gmail.com
License: BSD 3-Clause
Platform: UNKNOWN
Classifier: Programming Language :: Python :: 2
Classifier: Programming Language :: Python :: 3
Classifier: License :: OSI Approved :: BSD License
Classifier: Operating System :: OS Independent
Requires-Python: >=2.7
License-File: LICENSE
Requires-Dist: numpy
Requires-Dist: xarray
